pycodegen/__init__.py
pycodegen/cli.py
pycodegen/core.py
pycodegen/driver_base.py
pycodegen/frontend/__init__.py
pycodegen/frontend/frontend_cpp/__init__.py
pycodegen/frontend/frontend_cpp/class_decl.py
pycodegen/frontend/frontend_cpp/enum_decl.py
pycodegen/frontend/frontend_cpp/helpers.py
pycodegen/frontend/frontend_cpp/parser_libclang.py
pycodegen/frontend/frontend_json/__init__.py
pycodegen-0.0.1.dist-info/LICENSE
pycodegen-0.0.1.dist-info/METADATA
pycodegen-0.0.1.dist-info/WHEEL
pycodegen-0.0.1.dist-info/entry_points.txt
pycodegen-0.0.1.dist-info/top_level.txt
pycodegen-0.0.1.dist-info/RECORD
