Metadata-Version: 2.1
Name: pycodegen
Version: 0.0.1
Summary: Simple code generation tool with support for multiple types of inputs
Home-page: https://github.com/blejdfist/pycodegen
Author: Jim Persson
Author-email: jim@nurd.se
License: MIT
Keywords: code generation,libclang,codegenerator
Platform: any
Classifier: Development Status :: 3 - Alpha
Classifier: Programming Language :: Python :: 3.4
Classifier: Programming Language :: Python :: 3.5
Classifier: Programming Language :: Python :: 3.6
Classifier: Programming Language :: Python :: 3.7
Classifier: Programming Language :: Python :: 3.8
Classifier: Operating System :: OS Independent
Classifier: License :: OSI Approved :: MIT License
Classifier: Intended Audience :: Developers
Classifier: Topic :: Software Development
Classifier: Topic :: Software Development :: Build Tools
Classifier: Topic :: Software Development :: Pre-processors
Classifier: Topic :: Utilities
Requires-Python: >=3.4
Requires-Dist: jinja2 (>=2.10)
Provides-Extra: cpp
Requires-Dist: clang (>=5.0) ; extra == 'cpp'
